FaBo9Axis_MPU9250/MPU9250.py
FaBo9Axis_MPU9250/__init__.py
FaBo9Axis_MPU9250_Python3-1.0.3.dist-info/LICENSE
FaBo9Axis_MPU9250_Python3-1.0.3.dist-info/METADATA
FaBo9Axis_MPU9250_Python3-1.0.3.dist-info/WHEEL
FaBo9Axis_MPU9250_Python3-1.0.3.dist-info/top_level.txt
FaBo9Axis_MPU9250_Python3-1.0.3.dist-info/RECORD
